python_llk_model/__init__.py
python_llk_model/python_llk_model.py
python_llk_model-0.0.2.dist-info/LICENSE
python_llk_model-0.0.2.dist-info/METADATA
python_llk_model-0.0.2.dist-info/WHEEL
python_llk_model-0.0.2.dist-info/top_level.txt
python_llk_model-0.0.2.dist-info/RECORD
